cvkit/__init__.py
cvkit/utils.py
cvkit/pose_estimation/__init__.py
cvkit/pose_estimation/config.py
cvkit/pose_estimation/skeleton.py
cvkit/pose_estimation/utils.py
cvkit/pose_estimation/data_readers/__init__.py
cvkit/pose_estimation/data_readers/cvkit_datastore.py
cvkit/pose_estimation/data_readers/datastore_interface.py
cvkit/pose_estimation/data_readers/deeplabcut_datastore.py
cvkit/pose_estimation/data_readers/flattened_datastore.py
cvkit/pose_estimation/metrics/mpjpe.py
cvkit/pose_estimation/metrics/pck.py
cvkit/pose_estimation/processors/processor_interface.py
cvkit/pose_estimation/processors/filter/__init__.py
cvkit/pose_estimation/processors/filter/distance_statistics_filter.py
cvkit/pose_estimation/processors/filter/kalman_filter.py
cvkit/pose_estimation/processors/filter/linear_interpolation.py
cvkit/pose_estimation/processors/filter/median_distance_culling.py
cvkit/pose_estimation/processors/filter/moving_average.py
cvkit/pose_estimation/processors/filter/region_filter_2d.py
cvkit/pose_estimation/processors/filter/velocity_filter.py
cvkit/pose_estimation/processors/generative/__init__.py
cvkit/pose_estimation/processors/generative/dlt_deconstruct.py
cvkit/pose_estimation/processors/generative/dlt_reconstruct.py
cvkit/pose_estimation/processors/generative/generate_velocity_data.py
cvkit/pose_estimation/processors/util/__init__.py
cvkit/pose_estimation/processors/util/cluster_analysis.py
cvkit/pose_estimation/processors/util/load_file.py
cvkit/pose_estimation/processors/util/save_file.py
cvkit/pose_estimation/reconstruction/DLT.py
cvkit/pose_estimation/reconstruction/EasyWand_tools.py
cvkit/video_readers/__init__.py
cvkit/video_readers/cv2_reader.py
cvkit/video_readers/decord_reader.py
cvkit/video_readers/deffcode_reader.py
cvkit/video_readers/image_sequence_reader.py
cvkit/video_readers/video_reader_interface.py
bu_cvkit-0.0.3.1.dist-info/LICENSE
bu_cvkit-0.0.3.1.dist-info/METADATA
bu_cvkit-0.0.3.1.dist-info/WHEEL
bu_cvkit-0.0.3.1.dist-info/top_level.txt
bu_cvkit-0.0.3.1.dist-info/RECORD
