Metadata-Version: 2.1
Name: bu-cvkit
Version: 0.0.3.1
Summary: A toolkit to accelerate computer vision research
Author-email: Mahir Patel <mahirp@bu.edu>
Project-URL: repository, https://github.com/mahir1010/BU-CVKit
Classifier: Topic :: Scientific/Engineering :: Artificial Intelligence
Classifier: Programming Language :: Python :: 3
Classifier: License :: OSI Approved :: MIT License
Classifier: Operating System :: OS Independent
Requires-Python: <=3.11,>=3.10
License-File: LICENSE
Requires-Dist: deffcode (==0.2.5)
Requires-Dist: decord
Requires-Dist: filterpy (==1.4.5)
Requires-Dist: numpy (==1.24.2)
Requires-Dist: opencv-python-headless (==4.7.0.72)
Requires-Dist: pandas (==1.5.3)
Requires-Dist: PyYAML (==6.0)
Requires-Dist: scipy (==1.10.1)
Requires-Dist: tensorflow (==2.11.0)
